<?xml version="1.0" encoding="UTF-8"?>
<beans
	xsi:schemaLocation="http://www.springframework.org/schema/beans http://www.springframework.org/schema/beans/spring-beans-2.5.xsd"
	xmlns:xsi="http://www.w3.org/2001/XMLSchema-instance"
	xmlns="http://www.springframework.org/schema/beans">

	<bean
		class="org.springframework.transaction.interceptor.TransactionInterceptor"
		id="transactionInterceptor">
		<property ref="transactionManager" name="transactionManager" />
		<property name="transactionAttributes">
			<props>
				<prop key="save">PROPAGATION_REQUIRED</prop>
			</props>
		</property>
	</bean>
	<bean
		class="org.springframework.orm.hibernate3.HibernateTransactionManager"
		id="transactionManager">
		<property ref="dataSource" name="dataSource" />
		<property ref="sessionFactory" name="sessionFactory" />
	</bean>
</beans>